[{"id":"fixed-309","game":"SV","version":"Scarlet/Violet","source":"PKHeX.Core encounter_fixed_paldea.pkl","method":"Fixed Spawn","species":274,"speciesName":"Nuzleaf","speciesNameEn":"Nuzleaf","form":0,"levelMin":52,"levelMax":52,"location":164,"locationName":"Campos Prístinos de Noroteo","locationNameEn":"Kitakami Wilds","extraLocations":[164,166],"gender":"Random","genderCode":255,"ability":"Any12","shiny":"Random","shinyLocked":false,"fixedBall":null,"allowedBalls":"AnyLegalWildBall","flawlessIVCount":0,"teraType":"Normal","moves":[0,0,0,0],"nature":"Random"},{"id":"fixed-311","game":"SV","version":"Scarlet/Violet","source":"PKHeX.Core encounter_fixed_paldea.pkl","method":"Fixed Spawn","species":274,"speciesName":"Nuzleaf","speciesNameEn":"Nuzleaf","form":0,"levelMin":73,"levelMax":73,"location":164,"locationName":"Campos Prístinos de Noroteo","locationNameEn":"Kitakami Wilds","extraLocations":[164,166],"gender":"Random","genderCode":255,"ability":"Any12","shiny":"Random","shinyLocked":false,"fixedBall":null,"allowedBalls":"AnyLegalWildBall","flawlessIVCount":0,"teraType":"Normal","moves":[0,0,0,0],"nature":"Random"},{"id":"fixed-308","game":"SV","version":"Scarlet/Violet","source":"PKHeX.Core encounter_fixed_paldea.pkl","method":"Fixed Spawn","species":274,"speciesName":"Nuzleaf","speciesNameEn":"Nuzleaf","form":0,"levelMin":16,"levelMax":16,"location":140,"locationName":"Senda Jarana","locationNameEn":"Reveler’s Road","extraLocations":[140,158],"gender":"Random","genderCode":255,"ability":"Any12","shiny":"Random","shinyLocked":false,"fixedBall":null,"allowedBalls":"AnyLegalWildBall","flawlessIVCount":0,"teraType":"Normal","moves":[0,0,0,0],"nature":"Random"},{"id":"fixed-310","game":"SV","version":"Scarlet/Violet","source":"PKHeX.Core encounter_fixed_paldea.pkl","method":"Fixed Spawn","species":274,"speciesName":"Nuzleaf","speciesNameEn":"Nuzleaf","form":0,"levelMin":60,"levelMax":60,"location":140,"locationName":"Senda Jarana","locationNameEn":"Reveler’s Road","extraLocations":[140,158],"gender":"Random","genderCode":255,"ability":"Any12","shiny":"Random","shinyLocked":false,"fixedBall":null,"allowedBalls":"AnyLegalWildBall","flawlessIVCount":0,"teraType":"Normal","moves":[0,0,0,0],"nature":"Random"},{"id":"tera-kitakami-52","game":"SV","version":"Scarlet/Violet","source":"PKHeX.Core encounter_gem_kitakami.pkl","method":"Tera Raid","map":"Kitakami","species":274,"speciesName":"Nuzleaf","speciesNameEn":"Nuzleaf","form":0,"levelMin":35,"levelMax":35,"location":30024,"locationName":"Cueva cristalina","locationNameEn":"a crystal cavern","gender":"SpeciesRatio","genderCode":-1,"ability":"Any12H","shiny":"Random","shinyLocked":false,"fixedBall":null,"allowedBalls":"AnyLegalWildBall","flawlessIVCount":2,"teraType":"Fighting","moves":[75,36,252,371],"raidStars":3,"raidIndex":0,"randRate":100,"availableScarlet":true,"availableViolet":true,"nature":"Random"},{"id":"wild-302-56","game":"SV","version":"Scarlet/Violet","source":"PKHeX.Core encounter_wild_paldea.pkl","method":"Wild","areaIndex":302,"slotIndex":56,"species":274,"speciesName":"Nuzleaf","speciesNameEn":"Nuzleaf","form":0,"levelMin":30,"levelMax":39,"location":164,"locationName":"Campos Prístinos de Noroteo","locationNameEn":"Kitakami Wilds","gender":"Random","genderCode":255,"timeFlags":0,"weather":15,"shiny":"Random","shinyLocked":false,"isAlpha":false,"fixedBall":null,"allowedBalls":"AnyLegalWildBall","flawlessIVCount":0,"nature":"Random"},{"id":"wild-305-124","game":"SV","version":"Scarlet/Violet","source":"PKHeX.Core encounter_wild_paldea.pkl","method":"Wild","areaIndex":305,"slotIndex":124,"species":274,"speciesName":"Nuzleaf","speciesNameEn":"Nuzleaf","form":0,"levelMin":30,"levelMax":39,"location":164,"locationName":"Campos Prístinos de Noroteo","locationNameEn":"Kitakami Wilds","gender":"Random","genderCode":255,"timeFlags":0,"weather":15,"shiny":"Random","shinyLocked":false,"isAlpha":false,"fixedBall":null,"allowedBalls":"AnyLegalWildBall","flawlessIVCount":0,"nature":"Random"},{"id":"wild-305-125","game":"SV","version":"Scarlet/Violet","source":"PKHeX.Core encounter_wild_paldea.pkl","method":"Wild","areaIndex":305,"slotIndex":125,"species":274,"speciesName":"Nuzleaf","speciesNameEn":"Nuzleaf","form":0,"levelMin":30,"levelMax":39,"location":164,"locationName":"Campos Prístinos de Noroteo","locationNameEn":"Kitakami Wilds","gender":"Random","genderCode":255,"timeFlags":0,"weather":31,"shiny":"Random","shinyLocked":false,"isAlpha":false,"fixedBall":null,"allowedBalls":"AnyLegalWildBall","flawlessIVCount":0,"nature":"Random"},{"id":"wild-310-124","game":"SV","version":"Scarlet/Violet","source":"PKHeX.Core encounter_wild_paldea.pkl","method":"Wild","areaIndex":310,"slotIndex":124,"species":274,"speciesName":"Nuzleaf","speciesNameEn":"Nuzleaf","form":0,"levelMin":30,"levelMax":39,"location":164,"locationName":"Campos Prístinos de Noroteo","locationNameEn":"Kitakami Wilds","gender":"Random","genderCode":255,"timeFlags":0,"weather":15,"shiny":"Random","shinyLocked":false,"isAlpha":false,"fixedBall":null,"allowedBalls":"AnyLegalWildBall","flawlessIVCount":0,"nature":"Random"},{"id":"wild-310-125","game":"SV","version":"Scarlet/Violet","source":"PKHeX.Core encounter_wild_paldea.pkl","method":"Wild","areaIndex":310,"slotIndex":125,"species":274,"speciesName":"Nuzleaf","speciesNameEn":"Nuzleaf","form":0,"levelMin":30,"levelMax":39,"location":164,"locationName":"Campos Prístinos de Noroteo","locationNameEn":"Kitakami Wilds","gender":"Random","genderCode":255,"timeFlags":0,"weather":31,"shiny":"Random","shinyLocked":false,"isAlpha":false,"fixedBall":null,"allowedBalls":"AnyLegalWildBall","flawlessIVCount":0,"nature":"Random"},{"id":"wild-314-100","game":"SV","version":"Scarlet/Violet","source":"PKHeX.Core encounter_wild_paldea.pkl","method":"Wild","areaIndex":314,"slotIndex":100,"species":274,"speciesName":"Nuzleaf","speciesNameEn":"Nuzleaf","form":0,"levelMin":30,"levelMax":39,"location":164,"locationName":"Campos Prístinos de Noroteo","locationNameEn":"Kitakami Wilds","gender":"Random","genderCode":255,"timeFlags":0,"weather":15,"shiny":"Random","shinyLocked":false,"isAlpha":false,"fixedBall":null,"allowedBalls":"AnyLegalWildBall","flawlessIVCount":0,"nature":"Random"},{"id":"wild-314-101","game":"SV","version":"Scarlet/Violet","source":"PKHeX.Core encounter_wild_paldea.pkl","method":"Wild","areaIndex":314,"slotIndex":101,"species":274,"speciesName":"Nuzleaf","speciesNameEn":"Nuzleaf","form":0,"levelMin":30,"levelMax":39,"location":164,"locationName":"Campos Prístinos de Noroteo","locationNameEn":"Kitakami Wilds","gender":"Random","genderCode":255,"timeFlags":0,"weather":31,"shiny":"Random","shinyLocked":false,"isAlpha":false,"fixedBall":null,"allowedBalls":"AnyLegalWildBall","flawlessIVCount":0,"nature":"Random"},{"id":"wild-329-82","game":"SV","version":"Scarlet/Violet","source":"PKHeX.Core encounter_wild_paldea.pkl","method":"Wild","areaIndex":329,"slotIndex":82,"species":274,"speciesName":"Nuzleaf","speciesNameEn":"Nuzleaf","form":0,"levelMin":30,"levelMax":39,"location":164,"locationName":"Campos Prístinos de Noroteo","locationNameEn":"Kitakami Wilds","gender":"Random","genderCode":255,"timeFlags":0,"weather":15,"shiny":"Random","shinyLocked":false,"isAlpha":false,"fixedBall":null,"allowedBalls":"AnyLegalWildBall","flawlessIVCount":0,"nature":"Random"},{"id":"wild-329-83","game":"SV","version":"Scarlet/Violet","source":"PKHeX.Core encounter_wild_paldea.pkl","method":"Wild","areaIndex":329,"slotIndex":83,"species":274,"speciesName":"Nuzleaf","speciesNameEn":"Nuzleaf","form":0,"levelMin":30,"levelMax":39,"location":164,"locationName":"Campos Prístinos de Noroteo","locationNameEn":"Kitakami Wilds","gender":"Random","genderCode":255,"timeFlags":0,"weather":31,"shiny":"Random","shinyLocked":false,"isAlpha":false,"fixedBall":null,"allowedBalls":"AnyLegalWildBall","flawlessIVCount":0,"nature":"Random"},{"id":"wild-302-57","game":"SV","version":"Scarlet/Violet","source":"PKHeX.Core encounter_wild_paldea.pkl","method":"Wild","areaIndex":302,"slotIndex":57,"species":274,"speciesName":"Nuzleaf","speciesNameEn":"Nuzleaf","form":0,"levelMin":63,"levelMax":72,"location":164,"locationName":"Campos Prístinos de Noroteo","locationNameEn":"Kitakami Wilds","gender":"Random","genderCode":255,"timeFlags":0,"weather":15,"shiny":"Random","shinyLocked":false,"isAlpha":false,"fixedBall":null,"allowedBalls":"AnyLegalWildBall","flawlessIVCount":0,"nature":"Random"},{"id":"wild-305-126","game":"SV","version":"Scarlet/Violet","source":"PKHeX.Core encounter_wild_paldea.pkl","method":"Wild","areaIndex":305,"slotIndex":126,"species":274,"speciesName":"Nuzleaf","speciesNameEn":"Nuzleaf","form":0,"levelMin":63,"levelMax":72,"location":164,"locationName":"Campos Prístinos de Noroteo","locationNameEn":"Kitakami Wilds","gender":"Random","genderCode":255,"timeFlags":0,"weather":15,"shiny":"Random","shinyLocked":false,"isAlpha":false,"fixedBall":null,"allowedBalls":"AnyLegalWildBall","flawlessIVCount":0,"nature":"Random"},{"id":"wild-305-127","game":"SV","version":"Scarlet/Violet","source":"PKHeX.Core encounter_wild_paldea.pkl","method":"Wild","areaIndex":305,"slotIndex":127,"species":274,"speciesName":"Nuzleaf","speciesNameEn":"Nuzleaf","form":0,"levelMin":63,"levelMax":72,"location":164,"locationName":"Campos Prístinos de Noroteo","locationNameEn":"Kitakami Wilds","gender":"Random","genderCode":255,"timeFlags":0,"weather":31,"shiny":"Random","shinyLocked":false,"isAlpha":false,"fixedBall":null,"allowedBalls":"AnyLegalWildBall","flawlessIVCount":0,"nature":"Random"},{"id":"wild-310-126","game":"SV","version":"Scarlet/Violet","source":"PKHeX.Core encounter_wild_paldea.pkl","method":"Wild","areaIndex":310,"slotIndex":126,"species":274,"speciesName":"Nuzleaf","speciesNameEn":"Nuzleaf","form":0,"levelMin":63,"levelMax":72,"location":164,"locationName":"Campos Prístinos de Noroteo","locationNameEn":"Kitakami Wilds","gender":"Random","genderCode":255,"timeFlags":0,"weather":15,"shiny":"Random","shinyLocked":false,"isAlpha":false,"fixedBall":null,"allowedBalls":"AnyLegalWildBall","flawlessIVCount":0,"nature":"Random"},{"id":"wild-310-127","game":"SV","version":"Scarlet/Violet","source":"PKHeX.Core encounter_wild_paldea.pkl","method":"Wild","areaIndex":310,"slotIndex":127,"species":274,"speciesName":"Nuzleaf","speciesNameEn":"Nuzleaf","form":0,"levelMin":63,"levelMax":72,"location":164,"locationName":"Campos Prístinos de Noroteo","locationNameEn":"Kitakami Wilds","gender":"Random","genderCode":255,"timeFlags":0,"weather":31,"shiny":"Random","shinyLocked":false,"isAlpha":false,"fixedBall":null,"allowedBalls":"AnyLegalWildBall","flawlessIVCount":0,"nature":"Random"},{"id":"wild-314-102","game":"SV","version":"Scarlet/Violet","source":"PKHeX.Core encounter_wild_paldea.pkl","method":"Wild","areaIndex":314,"slotIndex":102,"species":274,"speciesName":"Nuzleaf","speciesNameEn":"Nuzleaf","form":0,"levelMin":63,"levelMax":72,"location":164,"locationName":"Campos Prístinos de Noroteo","locationNameEn":"Kitakami Wilds","gender":"Random","genderCode":255,"timeFlags":0,"weather":15,"shiny":"Random","shinyLocked":false,"isAlpha":false,"fixedBall":null,"allowedBalls":"AnyLegalWildBall","flawlessIVCount":0,"nature":"Random"},{"id":"wild-314-103","game":"SV","version":"Scarlet/Violet","source":"PKHeX.Core encounter_wild_paldea.pkl","method":"Wild","areaIndex":314,"slotIndex":103,"species":274,"speciesName":"Nuzleaf","speciesNameEn":"Nuzleaf","form":0,"levelMin":63,"levelMax":72,"location":164,"locationName":"Campos Prístinos de Noroteo","locationNameEn":"Kitakami Wilds","gender":"Random","genderCode":255,"timeFlags":0,"weather":31,"shiny":"Random","shinyLocked":false,"isAlpha":false,"fixedBall":null,"allowedBalls":"AnyLegalWildBall","flawlessIVCount":0,"nature":"Random"},{"id":"wild-329-84","game":"SV","version":"Scarlet/Violet","source":"PKHeX.Core encounter_wild_paldea.pkl","method":"Wild","areaIndex":329,"slotIndex":84,"species":274,"speciesName":"Nuzleaf","speciesNameEn":"Nuzleaf","form":0,"levelMin":63,"levelMax":72,"location":164,"locationName":"Campos Prístinos de Noroteo","locationNameEn":"Kitakami Wilds","gender":"Random","genderCode":255,"timeFlags":0,"weather":15,"shiny":"Random","shinyLocked":false,"isAlpha":false,"fixedBall":null,"allowedBalls":"AnyLegalWildBall","flawlessIVCount":0,"nature":"Random"},{"id":"wild-329-85","game":"SV","version":"Scarlet/Violet","source":"PKHeX.Core encounter_wild_paldea.pkl","method":"Wild","areaIndex":329,"slotIndex":85,"species":274,"speciesName":"Nuzleaf","speciesNameEn":"Nuzleaf","form":0,"levelMin":63,"levelMax":72,"location":164,"locationName":"Campos Prístinos de Noroteo","locationNameEn":"Kitakami Wilds","gender":"Random","genderCode":255,"timeFlags":0,"weather":31,"shiny":"Random","shinyLocked":false,"isAlpha":false,"fixedBall":null,"allowedBalls":"AnyLegalWildBall","flawlessIVCount":0,"nature":"Random"},{"id":"wild-267-24","game":"SV","version":"Scarlet/Violet","source":"PKHeX.Core encounter_wild_paldea.pkl","method":"Wild","areaIndex":267,"slotIndex":24,"species":274,"speciesName":"Nuzleaf","speciesNameEn":"Nuzleaf","form":0,"levelMin":27,"levelMax":34,"location":160,"locationName":"Desfiladero del Cuerno","locationNameEn":"Fellhorn Gorge","gender":"Random","genderCode":255,"timeFlags":0,"weather":15,"shiny":"Random","shinyLocked":false,"isAlpha":false,"fixedBall":null,"allowedBalls":"AnyLegalWildBall","flawlessIVCount":0,"nature":"Random"},{"id":"wild-276-67","game":"SV","version":"Scarlet/Violet","source":"PKHeX.Core encounter_wild_paldea.pkl","method":"Wild","areaIndex":276,"slotIndex":67,"species":274,"speciesName":"Nuzleaf","speciesNameEn":"Nuzleaf","form":0,"levelMin":27,"levelMax":34,"location":160,"locationName":"Desfiladero del Cuerno","locationNameEn":"Fellhorn Gorge","gender":"Random","genderCode":255,"timeFlags":0,"weather":15,"shiny":"Random","shinyLocked":false,"isAlpha":false,"fixedBall":null,"allowedBalls":"AnyLegalWildBall","flawlessIVCount":0,"nature":"Random"},{"id":"wild-280-67","game":"SV","version":"Scarlet/Violet","source":"PKHeX.Core encounter_wild_paldea.pkl","method":"Wild","areaIndex":280,"slotIndex":67,"species":274,"speciesName":"Nuzleaf","speciesNameEn":"Nuzleaf","form":0,"levelMin":27,"levelMax":34,"location":160,"locationName":"Desfiladero del Cuerno","locationNameEn":"Fellhorn Gorge","gender":"Random","genderCode":255,"timeFlags":0,"weather":15,"shiny":"Random","shinyLocked":false,"isAlpha":false,"fixedBall":null,"allowedBalls":"AnyLegalWildBall","flawlessIVCount":0,"nature":"Random"},{"id":"wild-267-25","game":"SV","version":"Scarlet/Violet","source":"PKHeX.Core encounter_wild_paldea.pkl","method":"Wild","areaIndex":267,"slotIndex":25,"species":274,"speciesName":"Nuzleaf","speciesNameEn":"Nuzleaf","form":0,"levelMin":65,"levelMax":72,"location":160,"locationName":"Desfiladero del Cuerno","locationNameEn":"Fellhorn Gorge","gender":"Random","genderCode":255,"timeFlags":0,"weather":15,"shiny":"Random","shinyLocked":false,"isAlpha":false,"fixedBall":null,"allowedBalls":"AnyLegalWildBall","flawlessIVCount":0,"nature":"Random"},{"id":"wild-276-68","game":"SV","version":"Scarlet/Violet","source":"PKHeX.Core encounter_wild_paldea.pkl","method":"Wild","areaIndex":276,"slotIndex":68,"species":274,"speciesName":"Nuzleaf","speciesNameEn":"Nuzleaf","form":0,"levelMin":65,"levelMax":72,"location":160,"locationName":"Desfiladero del Cuerno","locationNameEn":"Fellhorn Gorge","gender":"Random","genderCode":255,"timeFlags":0,"weather":15,"shiny":"Random","shinyLocked":false,"isAlpha":false,"fixedBall":null,"allowedBalls":"AnyLegalWildBall","flawlessIVCount":0,"nature":"Random"},{"id":"wild-280-68","game":"SV","version":"Scarlet/Violet","source":"PKHeX.Core encounter_wild_paldea.pkl","method":"Wild","areaIndex":280,"slotIndex":68,"species":274,"speciesName":"Nuzleaf","speciesNameEn":"Nuzleaf","form":0,"levelMin":65,"levelMax":72,"location":160,"locationName":"Desfiladero del Cuerno","locationNameEn":"Fellhorn Gorge","gender":"Random","genderCode":255,"timeFlags":0,"weather":15,"shiny":"Random","shinyLocked":false,"isAlpha":false,"fixedBall":null,"allowedBalls":"AnyLegalWildBall","flawlessIVCount":0,"nature":"Random"},{"id":"wild-309-50","game":"SV","version":"Scarlet/Violet","source":"PKHeX.Core encounter_wild_paldea.pkl","method":"Wild","areaIndex":309,"slotIndex":50,"species":274,"speciesName":"Nuzleaf","speciesNameEn":"Nuzleaf","form":0,"levelMin":19,"levelMax":22,"location":162,"locationName":"Elíseo Baldío","locationNameEn":"Paradise Barrens","gender":"Random","genderCode":255,"timeFlags":0,"weather":15,"shiny":"Random","shinyLocked":false,"isAlpha":false,"fixedBall":null,"allowedBalls":"AnyLegalWildBall","flawlessIVCount":0,"nature":"Random"},{"id":"wild-325-72","game":"SV","version":"Scarlet/Violet","source":"PKHeX.Core encounter_wild_paldea.pkl","method":"Wild","areaIndex":325,"slotIndex":72,"species":274,"speciesName":"Nuzleaf","speciesNameEn":"Nuzleaf","form":0,"levelMin":19,"levelMax":22,"location":162,"locationName":"Elíseo Baldío","locationNameEn":"Paradise Barrens","gender":"Random","genderCode":255,"timeFlags":0,"weather":15,"shiny":"Random","shinyLocked":false,"isAlpha":false,"fixedBall":null,"allowedBalls":"AnyLegalWildBall","flawlessIVCount":0,"nature":"Random"},{"id":"wild-330-72","game":"SV","version":"Scarlet/Violet","source":"PKHeX.Core encounter_wild_paldea.pkl","method":"Wild","areaIndex":330,"slotIndex":72,"species":274,"speciesName":"Nuzleaf","speciesNameEn":"Nuzleaf","form":0,"levelMin":19,"levelMax":22,"location":162,"locationName":"Elíseo Baldío","locationNameEn":"Paradise Barrens","gender":"Random","genderCode":255,"timeFlags":0,"weather":15,"shiny":"Random","shinyLocked":false,"isAlpha":false,"fixedBall":null,"allowedBalls":"AnyLegalWildBall","flawlessIVCount":0,"nature":"Random"},{"id":"wild-309-51","game":"SV","version":"Scarlet/Violet","source":"PKHeX.Core encounter_wild_paldea.pkl","method":"Wild","areaIndex":309,"slotIndex":51,"species":274,"speciesName":"Nuzleaf","speciesNameEn":"Nuzleaf","form":0,"levelMin":62,"levelMax":65,"location":162,"locationName":"Elíseo Baldío","locationNameEn":"Paradise Barrens","gender":"Random","genderCode":255,"timeFlags":0,"weather":15,"shiny":"Random","shinyLocked":false,"isAlpha":false,"fixedBall":null,"allowedBalls":"AnyLegalWildBall","flawlessIVCount":0,"nature":"Random"},{"id":"wild-325-73","game":"SV","version":"Scarlet/Violet","source":"PKHeX.Core encounter_wild_paldea.pkl","method":"Wild","areaIndex":325,"slotIndex":73,"species":274,"speciesName":"Nuzleaf","speciesNameEn":"Nuzleaf","form":0,"levelMin":62,"levelMax":65,"location":162,"locationName":"Elíseo Baldío","locationNameEn":"Paradise Barrens","gender":"Random","genderCode":255,"timeFlags":0,"weather":15,"shiny":"Random","shinyLocked":false,"isAlpha":false,"fixedBall":null,"allowedBalls":"AnyLegalWildBall","flawlessIVCount":0,"nature":"Random"},{"id":"wild-330-73","game":"SV","version":"Scarlet/Violet","source":"PKHeX.Core encounter_wild_paldea.pkl","method":"Wild","areaIndex":330,"slotIndex":73,"species":274,"speciesName":"Nuzleaf","speciesNameEn":"Nuzleaf","form":0,"levelMin":62,"levelMax":65,"location":162,"locationName":"Elíseo Baldío","locationNameEn":"Paradise Barrens","gender":"Random","genderCode":255,"timeFlags":0,"weather":15,"shiny":"Random","shinyLocked":false,"isAlpha":false,"fixedBall":null,"allowedBalls":"AnyLegalWildBall","flawlessIVCount":0,"nature":"Random"},{"id":"wild-290-134","game":"SV","version":"Scarlet/Violet","source":"PKHeX.Core encounter_wild_paldea.pkl","method":"Wild","areaIndex":290,"slotIndex":134,"species":274,"speciesName":"Nuzleaf","speciesNameEn":"Nuzleaf","form":0,"levelMin":24,"levelMax":27,"location":144,"locationName":"Monte Ogro","locationNameEn":"Oni Mountain","gender":"Random","genderCode":255,"timeFlags":0,"weather":15,"shiny":"Random","shinyLocked":false,"isAlpha":false,"fixedBall":null,"allowedBalls":"AnyLegalWildBall","flawlessIVCount":0,"nature":"Random"},{"id":"wild-293-134","game":"SV","version":"Scarlet/Violet","source":"PKHeX.Core encounter_wild_paldea.pkl","method":"Wild","areaIndex":293,"slotIndex":134,"species":274,"speciesName":"Nuzleaf","speciesNameEn":"Nuzleaf","form":0,"levelMin":24,"levelMax":27,"location":144,"locationName":"Monte Ogro","locationNameEn":"Oni Mountain","gender":"Random","genderCode":255,"timeFlags":0,"weather":15,"shiny":"Random","shinyLocked":false,"isAlpha":false,"fixedBall":null,"allowedBalls":"AnyLegalWildBall","flawlessIVCount":0,"nature":"Random"},{"id":"wild-306-34","game":"SV","version":"Scarlet/Violet","source":"PKHeX.Core encounter_wild_paldea.pkl","method":"Wild","areaIndex":306,"slotIndex":34,"species":274,"speciesName":"Nuzleaf","speciesNameEn":"Nuzleaf","form":0,"levelMin":24,"levelMax":27,"location":144,"locationName":"Monte Ogro","locationNameEn":"Oni Mountain","gender":"Random","genderCode":255,"timeFlags":0,"weather":15,"shiny":"Random","shinyLocked":false,"isAlpha":false,"fixedBall":null,"allowedBalls":"AnyLegalWildBall","flawlessIVCount":0,"nature":"Random"},{"id":"wild-290-135","game":"SV","version":"Scarlet/Violet","source":"PKHeX.Core encounter_wild_paldea.pkl","method":"Wild","areaIndex":290,"slotIndex":135,"species":274,"speciesName":"Nuzleaf","speciesNameEn":"Nuzleaf","form":0,"levelMin":65,"levelMax":68,"location":144,"locationName":"Monte Ogro","locationNameEn":"Oni Mountain","gender":"Random","genderCode":255,"timeFlags":0,"weather":15,"shiny":"Random","shinyLocked":false,"isAlpha":false,"fixedBall":null,"allowedBalls":"AnyLegalWildBall","flawlessIVCount":0,"nature":"Random"},{"id":"wild-293-135","game":"SV","version":"Scarlet/Violet","source":"PKHeX.Core encounter_wild_paldea.pkl","method":"Wild","areaIndex":293,"slotIndex":135,"species":274,"speciesName":"Nuzleaf","speciesNameEn":"Nuzleaf","form":0,"levelMin":65,"levelMax":68,"location":144,"locationName":"Monte Ogro","locationNameEn":"Oni Mountain","gender":"Random","genderCode":255,"timeFlags":0,"weather":15,"shiny":"Random","shinyLocked":false,"isAlpha":false,"fixedBall":null,"allowedBalls":"AnyLegalWildBall","flawlessIVCount":0,"nature":"Random"},{"id":"wild-306-35","game":"SV","version":"Scarlet/Violet","source":"PKHeX.Core encounter_wild_paldea.pkl","method":"Wild","areaIndex":306,"slotIndex":35,"species":274,"speciesName":"Nuzleaf","speciesNameEn":"Nuzleaf","form":0,"levelMin":65,"levelMax":68,"location":144,"locationName":"Monte Ogro","locationNameEn":"Oni Mountain","gender":"Random","genderCode":255,"timeFlags":0,"weather":15,"shiny":"Random","shinyLocked":false,"isAlpha":false,"fixedBall":null,"allowedBalls":"AnyLegalWildBall","flawlessIVCount":0,"nature":"Random"},{"id":"wild-265-170","game":"SV","version":"Scarlet/Violet","source":"PKHeX.Core encounter_wild_paldea.pkl","method":"Wild","areaIndex":265,"slotIndex":170,"species":274,"speciesName":"Nuzleaf","speciesNameEn":"Nuzleaf","form":0,"levelMin":14,"levelMax":16,"location":158,"locationName":"Ribera Confluencia","locationNameEn":"Mossfell Confluence","gender":"Random","genderCode":255,"timeFlags":0,"weather":15,"shiny":"Random","shinyLocked":false,"isAlpha":false,"fixedBall":null,"allowedBalls":"AnyLegalWildBall","flawlessIVCount":0,"nature":"Random"},{"id":"wild-265-171","game":"SV","version":"Scarlet/Violet","source":"PKHeX.Core encounter_wild_paldea.pkl","method":"Wild","areaIndex":265,"slotIndex":171,"species":274,"speciesName":"Nuzleaf","speciesNameEn":"Nuzleaf","form":0,"levelMin":14,"levelMax":16,"location":158,"locationName":"Ribera Confluencia","locationNameEn":"Mossfell Confluence","gender":"Random","genderCode":255,"timeFlags":0,"weather":31,"shiny":"Random","shinyLocked":false,"isAlpha":false,"fixedBall":null,"allowedBalls":"AnyLegalWildBall","flawlessIVCount":0,"nature":"Random"},{"id":"wild-268-132","game":"SV","version":"Scarlet/Violet","source":"PKHeX.Core encounter_wild_paldea.pkl","method":"Wild","areaIndex":268,"slotIndex":132,"species":274,"speciesName":"Nuzleaf","speciesNameEn":"Nuzleaf","form":0,"levelMin":14,"levelMax":16,"location":158,"locationName":"Ribera Confluencia","locationNameEn":"Mossfell Confluence","gender":"Random","genderCode":255,"timeFlags":0,"weather":15,"shiny":"Random","shinyLocked":false,"isAlpha":false,"fixedBall":null,"allowedBalls":"AnyLegalWildBall","flawlessIVCount":0,"nature":"Random"},{"id":"wild-268-133","game":"SV","version":"Scarlet/Violet","source":"PKHeX.Core encounter_wild_paldea.pkl","method":"Wild","areaIndex":268,"slotIndex":133,"species":274,"speciesName":"Nuzleaf","speciesNameEn":"Nuzleaf","form":0,"levelMin":14,"levelMax":16,"location":158,"locationName":"Ribera Confluencia","locationNameEn":"Mossfell Confluence","gender":"Random","genderCode":255,"timeFlags":0,"weather":31,"shiny":"Random","shinyLocked":false,"isAlpha":false,"fixedBall":null,"allowedBalls":"AnyLegalWildBall","flawlessIVCount":0,"nature":"Random"},{"id":"wild-335-131","game":"SV","version":"Scarlet/Violet","source":"PKHeX.Core encounter_wild_paldea.pkl","method":"Wild","areaIndex":335,"slotIndex":131,"species":274,"speciesName":"Nuzleaf","speciesNameEn":"Nuzleaf","form":0,"levelMin":14,"levelMax":16,"location":158,"locationName":"Ribera Confluencia","locationNameEn":"Mossfell Confluence","gender":"Random","genderCode":255,"timeFlags":0,"weather":15,"shiny":"Random","shinyLocked":false,"isAlpha":false,"fixedBall":null,"allowedBalls":"AnyLegalWildBall","flawlessIVCount":0,"nature":"Random"},{"id":"wild-335-132","game":"SV","version":"Scarlet/Violet","source":"PKHeX.Core encounter_wild_paldea.pkl","method":"Wild","areaIndex":335,"slotIndex":132,"species":274,"speciesName":"Nuzleaf","speciesNameEn":"Nuzleaf","form":0,"levelMin":14,"levelMax":16,"location":158,"locationName":"Ribera Confluencia","locationNameEn":"Mossfell Confluence","gender":"Random","genderCode":255,"timeFlags":0,"weather":31,"shiny":"Random","shinyLocked":false,"isAlpha":false,"fixedBall":null,"allowedBalls":"AnyLegalWildBall","flawlessIVCount":0,"nature":"Random"},{"id":"wild-344-33","game":"SV","version":"Scarlet/Violet","source":"PKHeX.Core encounter_wild_paldea.pkl","method":"Wild","areaIndex":344,"slotIndex":33,"species":274,"speciesName":"Nuzleaf","speciesNameEn":"Nuzleaf","form":0,"levelMin":14,"levelMax":16,"location":158,"locationName":"Ribera Confluencia","locationNameEn":"Mossfell Confluence","gender":"Random","genderCode":255,"timeFlags":0,"weather":31,"shiny":"Random","shinyLocked":false,"isAlpha":false,"fixedBall":null,"allowedBalls":"AnyLegalWildBall","flawlessIVCount":0,"nature":"Random"},{"id":"wild-256-25","game":"SV","version":"Scarlet/Violet","source":"PKHeX.Core encounter_wild_paldea.pkl","method":"Wild","areaIndex":256,"slotIndex":25,"species":274,"speciesName":"Nuzleaf","speciesNameEn":"Nuzleaf","form":0,"levelMin":18,"levelMax":21,"location":158,"locationName":"Ribera Confluencia","locationNameEn":"Mossfell Confluence","gender":"Random","genderCode":255,"timeFlags":0,"weather":31,"shiny":"Random","shinyLocked":false,"isAlpha":false,"fixedBall":null,"allowedBalls":"AnyLegalWildBall","flawlessIVCount":0,"nature":"Random"},{"id":"wild-265-172","game":"SV","version":"Scarlet/Violet","source":"PKHeX.Core encounter_wild_paldea.pkl","method":"Wild","areaIndex":265,"slotIndex":172,"species":274,"speciesName":"Nuzleaf","speciesNameEn":"Nuzleaf","form":0,"levelMin":18,"levelMax":25,"location":158,"locationName":"Ribera Confluencia","locationNameEn":"Mossfell Confluence","gender":"Random","genderCode":255,"timeFlags":0,"weather":31,"shiny":"Random","shinyLocked":false,"isAlpha":false,"fixedBall":null,"allowedBalls":"AnyLegalWildBall","flawlessIVCount":0,"nature":"Random"},{"id":"wild-328-38","game":"SV","version":"Scarlet/Violet","source":"PKHeX.Core encounter_wild_paldea.pkl","method":"Wild","areaIndex":328,"slotIndex":38,"species":274,"speciesName":"Nuzleaf","speciesNameEn":"Nuzleaf","form":0,"levelMin":18,"levelMax":21,"location":158,"locationName":"Ribera Confluencia","locationNameEn":"Mossfell Confluence","gender":"Random","genderCode":255,"timeFlags":0,"weather":31,"shiny":"Random","shinyLocked":false,"isAlpha":false,"fixedBall":null,"allowedBalls":"AnyLegalWildBall","flawlessIVCount":0,"nature":"Random"},{"id":"wild-265-173","game":"SV","version":"Scarlet/Violet","source":"PKHeX.Core encounter_wild_paldea.pkl","method":"Wild","areaIndex":265,"slotIndex":173,"species":274,"speciesName":"Nuzleaf","speciesNameEn":"Nuzleaf","form":0,"levelMin":19,"levelMax":25,"location":158,"locationName":"Ribera Confluencia","locationNameEn":"Mossfell Confluence","gender":"Random","genderCode":255,"timeFlags":0,"weather":15,"shiny":"Random","shinyLocked":false,"isAlpha":false,"fixedBall":null,"allowedBalls":"AnyLegalWildBall","flawlessIVCount":0,"nature":"Random"},{"id":"wild-268-134","game":"SV","version":"Scarlet/Violet","source":"PKHeX.Core encounter_wild_paldea.pkl","method":"Wild","areaIndex":268,"slotIndex":134,"species":274,"speciesName":"Nuzleaf","speciesNameEn":"Nuzleaf","form":0,"levelMin":19,"levelMax":25,"location":158,"locationName":"Ribera Confluencia","locationNameEn":"Mossfell Confluence","gender":"Random","genderCode":255,"timeFlags":0,"weather":15,"shiny":"Random","shinyLocked":false,"isAlpha":false,"fixedBall":null,"allowedBalls":"AnyLegalWildBall","flawlessIVCount":0,"nature":"Random"},{"id":"wild-268-135","game":"SV","version":"Scarlet/Violet","source":"PKHeX.Core encounter_wild_paldea.pkl","method":"Wild","areaIndex":268,"slotIndex":135,"species":274,"speciesName":"Nuzleaf","speciesNameEn":"Nuzleaf","form":0,"levelMin":19,"levelMax":25,"location":158,"locationName":"Ribera Confluencia","locationNameEn":"Mossfell Confluence","gender":"Random","genderCode":255,"timeFlags":0,"weather":31,"shiny":"Random","shinyLocked":false,"isAlpha":false,"fixedBall":null,"allowedBalls":"AnyLegalWildBall","flawlessIVCount":0,"nature":"Random"},{"id":"wild-278-74","game":"SV","version":"Scarlet/Violet","source":"PKHeX.Core encounter_wild_paldea.pkl","method":"Wild","areaIndex":278,"slotIndex":74,"species":274,"speciesName":"Nuzleaf","speciesNameEn":"Nuzleaf","form":0,"levelMin":19,"levelMax":25,"location":158,"locationName":"Ribera Confluencia","locationNameEn":"Mossfell Confluence","gender":"Random","genderCode":255,"timeFlags":0,"weather":15,"shiny":"Random","shinyLocked":false,"isAlpha":false,"fixedBall":null,"allowedBalls":"AnyLegalWildBall","flawlessIVCount":0,"nature":"Random"},{"id":"wild-278-75","game":"SV","version":"Scarlet/Violet","source":"PKHeX.Core encounter_wild_paldea.pkl","method":"Wild","areaIndex":278,"slotIndex":75,"species":274,"speciesName":"Nuzleaf","speciesNameEn":"Nuzleaf","form":0,"levelMin":19,"levelMax":25,"location":158,"locationName":"Ribera Confluencia","locationNameEn":"Mossfell Confluence","gender":"Random","genderCode":255,"timeFlags":0,"weather":31,"shiny":"Random","shinyLocked":false,"isAlpha":false,"fixedBall":null,"allowedBalls":"AnyLegalWildBall","flawlessIVCount":0,"nature":"Random"},{"id":"wild-335-133","game":"SV","version":"Scarlet/Violet","source":"PKHeX.Core encounter_wild_paldea.pkl","method":"Wild","areaIndex":335,"slotIndex":133,"species":274,"speciesName":"Nuzleaf","speciesNameEn":"Nuzleaf","form":0,"levelMin":19,"levelMax":25,"location":158,"locationName":"Ribera Confluencia","locationNameEn":"Mossfell Confluence","gender":"Random","genderCode":255,"timeFlags":0,"weather":15,"shiny":"Random","shinyLocked":false,"isAlpha":false,"fixedBall":null,"allowedBalls":"AnyLegalWildBall","flawlessIVCount":0,"nature":"Random"},{"id":"wild-335-134","game":"SV","version":"Scarlet/Violet","source":"PKHeX.Core encounter_wild_paldea.pkl","method":"Wild","areaIndex":335,"slotIndex":134,"species":274,"speciesName":"Nuzleaf","speciesNameEn":"Nuzleaf","form":0,"levelMin":19,"levelMax":25,"location":158,"locationName":"Ribera Confluencia","locationNameEn":"Mossfell Confluence","gender":"Random","genderCode":255,"timeFlags":0,"weather":31,"shiny":"Random","shinyLocked":false,"isAlpha":false,"fixedBall":null,"allowedBalls":"AnyLegalWildBall","flawlessIVCount":0,"nature":"Random"},{"id":"wild-265-174","game":"SV","version":"Scarlet/Violet","source":"PKHeX.Core encounter_wild_paldea.pkl","method":"Wild","areaIndex":265,"slotIndex":174,"species":274,"speciesName":"Nuzleaf","speciesNameEn":"Nuzleaf","form":0,"levelMin":30,"levelMax":39,"location":158,"locationName":"Ribera Confluencia","locationNameEn":"Mossfell Confluence","gender":"Random","genderCode":255,"timeFlags":0,"weather":31,"shiny":"Random","shinyLocked":false,"isAlpha":false,"fixedBall":null,"allowedBalls":"AnyLegalWildBall","flawlessIVCount":0,"nature":"Random"},{"id":"wild-307-27","game":"SV","version":"Scarlet/Violet","source":"PKHeX.Core encounter_wild_paldea.pkl","method":"Wild","areaIndex":307,"slotIndex":27,"species":274,"speciesName":"Nuzleaf","speciesNameEn":"Nuzleaf","form":0,"levelMin":30,"levelMax":39,"location":158,"locationName":"Ribera Confluencia","locationNameEn":"Mossfell Confluence","gender":"Random","genderCode":255,"timeFlags":0,"weather":31,"shiny":"Random","shinyLocked":false,"isAlpha":false,"fixedBall":null,"allowedBalls":"AnyLegalWildBall","flawlessIVCount":0,"nature":"Random"},{"id":"wild-328-39","game":"SV","version":"Scarlet/Violet","source":"PKHeX.Core encounter_wild_paldea.pkl","method":"Wild","areaIndex":328,"slotIndex":39,"species":274,"speciesName":"Nuzleaf","speciesNameEn":"Nuzleaf","form":0,"levelMin":30,"levelMax":39,"location":158,"locationName":"Ribera Confluencia","locationNameEn":"Mossfell Confluence","gender":"Random","genderCode":255,"timeFlags":0,"weather":31,"shiny":"Random","shinyLocked":false,"isAlpha":false,"fixedBall":null,"allowedBalls":"AnyLegalWildBall","flawlessIVCount":0,"nature":"Random"},{"id":"wild-265-175","game":"SV","version":"Scarlet/Violet","source":"PKHeX.Core encounter_wild_paldea.pkl","method":"Wild","areaIndex":265,"slotIndex":175,"species":274,"speciesName":"Nuzleaf","speciesNameEn":"Nuzleaf","form":0,"levelMin":62,"levelMax":68,"location":158,"locationName":"Ribera Confluencia","locationNameEn":"Mossfell Confluence","gender":"Random","genderCode":255,"timeFlags":0,"weather":15,"shiny":"Random","shinyLocked":false,"isAlpha":false,"fixedBall":null,"allowedBalls":"AnyLegalWildBall","flawlessIVCount":0,"nature":"Random"},{"id":"wild-265-176","game":"SV","version":"Scarlet/Violet","source":"PKHeX.Core encounter_wild_paldea.pkl","method":"Wild","areaIndex":265,"slotIndex":176,"species":274,"speciesName":"Nuzleaf","speciesNameEn":"Nuzleaf","form":0,"levelMin":62,"levelMax":68,"location":158,"locationName":"Ribera Confluencia","locationNameEn":"Mossfell Confluence","gender":"Random","genderCode":255,"timeFlags":0,"weather":31,"shiny":"Random","shinyLocked":false,"isAlpha":false,"fixedBall":null,"allowedBalls":"AnyLegalWildBall","flawlessIVCount":0,"nature":"Random"},{"id":"wild-268-136","game":"SV","version":"Scarlet/Violet","source":"PKHeX.Core encounter_wild_paldea.pkl","method":"Wild","areaIndex":268,"slotIndex":136,"species":274,"speciesName":"Nuzleaf","speciesNameEn":"Nuzleaf","form":0,"levelMin":62,"levelMax":68,"location":158,"locationName":"Ribera Confluencia","locationNameEn":"Mossfell Confluence","gender":"Random","genderCode":255,"timeFlags":0,"weather":15,"shiny":"Random","shinyLocked":false,"isAlpha":false,"fixedBall":null,"allowedBalls":"AnyLegalWildBall","flawlessIVCount":0,"nature":"Random"},{"id":"wild-268-137","game":"SV","version":"Scarlet/Violet","source":"PKHeX.Core encounter_wild_paldea.pkl","method":"Wild","areaIndex":268,"slotIndex":137,"species":274,"speciesName":"Nuzleaf","speciesNameEn":"Nuzleaf","form":0,"levelMin":62,"levelMax":68,"location":158,"locationName":"Ribera Confluencia","locationNameEn":"Mossfell Confluence","gender":"Random","genderCode":255,"timeFlags":0,"weather":31,"shiny":"Random","shinyLocked":false,"isAlpha":false,"fixedBall":null,"allowedBalls":"AnyLegalWildBall","flawlessIVCount":0,"nature":"Random"},{"id":"wild-278-76","game":"SV","version":"Scarlet/Violet","source":"PKHeX.Core encounter_wild_paldea.pkl","method":"Wild","areaIndex":278,"slotIndex":76,"species":274,"speciesName":"Nuzleaf","speciesNameEn":"Nuzleaf","form":0,"levelMin":62,"levelMax":68,"location":158,"locationName":"Ribera Confluencia","locationNameEn":"Mossfell Confluence","gender":"Random","genderCode":255,"timeFlags":0,"weather":15,"shiny":"Random","shinyLocked":false,"isAlpha":false,"fixedBall":null,"allowedBalls":"AnyLegalWildBall","flawlessIVCount":0,"nature":"Random"},{"id":"wild-278-77","game":"SV","version":"Scarlet/Violet","source":"PKHeX.Core encounter_wild_paldea.pkl","method":"Wild","areaIndex":278,"slotIndex":77,"species":274,"speciesName":"Nuzleaf","speciesNameEn":"Nuzleaf","form":0,"levelMin":62,"levelMax":68,"location":158,"locationName":"Ribera Confluencia","locationNameEn":"Mossfell Confluence","gender":"Random","genderCode":255,"timeFlags":0,"weather":31,"shiny":"Random","shinyLocked":false,"isAlpha":false,"fixedBall":null,"allowedBalls":"AnyLegalWildBall","flawlessIVCount":0,"nature":"Random"},{"id":"wild-335-135","game":"SV","version":"Scarlet/Violet","source":"PKHeX.Core encounter_wild_paldea.pkl","method":"Wild","areaIndex":335,"slotIndex":135,"species":274,"speciesName":"Nuzleaf","speciesNameEn":"Nuzleaf","form":0,"levelMin":62,"levelMax":68,"location":158,"locationName":"Ribera Confluencia","locationNameEn":"Mossfell Confluence","gender":"Random","genderCode":255,"timeFlags":0,"weather":15,"shiny":"Random","shinyLocked":false,"isAlpha":false,"fixedBall":null,"allowedBalls":"AnyLegalWildBall","flawlessIVCount":0,"nature":"Random"},{"id":"wild-335-136","game":"SV","version":"Scarlet/Violet","source":"PKHeX.Core encounter_wild_paldea.pkl","method":"Wild","areaIndex":335,"slotIndex":136,"species":274,"speciesName":"Nuzleaf","speciesNameEn":"Nuzleaf","form":0,"levelMin":62,"levelMax":68,"location":158,"locationName":"Ribera Confluencia","locationNameEn":"Mossfell Confluence","gender":"Random","genderCode":255,"timeFlags":0,"weather":31,"shiny":"Random","shinyLocked":false,"isAlpha":false,"fixedBall":null,"allowedBalls":"AnyLegalWildBall","flawlessIVCount":0,"nature":"Random"},{"id":"wild-266-76","game":"SV","version":"Scarlet/Violet","source":"PKHeX.Core encounter_wild_paldea.pkl","method":"Wild","areaIndex":266,"slotIndex":76,"species":274,"speciesName":"Nuzleaf","speciesNameEn":"Nuzleaf","form":0,"levelMin":14,"levelMax":16,"location":140,"locationName":"Senda Jarana","locationNameEn":"Reveler’s Road","gender":"Random","genderCode":255,"timeFlags":0,"weather":15,"shiny":"Random","shinyLocked":false,"isAlpha":false,"fixedBall":null,"allowedBalls":"AnyLegalWildBall","flawlessIVCount":0,"nature":"Random"},{"id":"wild-266-77","game":"SV","version":"Scarlet/Violet","source":"PKHeX.Core encounter_wild_paldea.pkl","method":"Wild","areaIndex":266,"slotIndex":77,"species":274,"speciesName":"Nuzleaf","speciesNameEn":"Nuzleaf","form":0,"levelMin":14,"levelMax":16,"location":140,"locationName":"Senda Jarana","locationNameEn":"Reveler’s Road","gender":"Random","genderCode":255,"timeFlags":0,"weather":31,"shiny":"Random","shinyLocked":false,"isAlpha":false,"fixedBall":null,"allowedBalls":"AnyLegalWildBall","flawlessIVCount":0,"nature":"Random"},{"id":"wild-331-84","game":"SV","version":"Scarlet/Violet","source":"PKHeX.Core encounter_wild_paldea.pkl","method":"Wild","areaIndex":331,"slotIndex":84,"species":274,"speciesName":"Nuzleaf","speciesNameEn":"Nuzleaf","form":0,"levelMin":14,"levelMax":16,"location":140,"locationName":"Senda Jarana","locationNameEn":"Reveler’s Road","gender":"Random","genderCode":255,"timeFlags":0,"weather":15,"shiny":"Random","shinyLocked":false,"isAlpha":false,"fixedBall":null,"allowedBalls":"AnyLegalWildBall","flawlessIVCount":0,"nature":"Random"},{"id":"wild-331-85","game":"SV","version":"Scarlet/Violet","source":"PKHeX.Core encounter_wild_paldea.pkl","method":"Wild","areaIndex":331,"slotIndex":85,"species":274,"speciesName":"Nuzleaf","speciesNameEn":"Nuzleaf","form":0,"levelMin":14,"levelMax":16,"location":140,"locationName":"Senda Jarana","locationNameEn":"Reveler’s Road","gender":"Random","genderCode":255,"timeFlags":0,"weather":31,"shiny":"Random","shinyLocked":false,"isAlpha":false,"fixedBall":null,"allowedBalls":"AnyLegalWildBall","flawlessIVCount":0,"nature":"Random"},{"id":"wild-338-84","game":"SV","version":"Scarlet/Violet","source":"PKHeX.Core encounter_wild_paldea.pkl","method":"Wild","areaIndex":338,"slotIndex":84,"species":274,"speciesName":"Nuzleaf","speciesNameEn":"Nuzleaf","form":0,"levelMin":14,"levelMax":16,"location":140,"locationName":"Senda Jarana","locationNameEn":"Reveler’s Road","gender":"Random","genderCode":255,"timeFlags":0,"weather":15,"shiny":"Random","shinyLocked":false,"isAlpha":false,"fixedBall":null,"allowedBalls":"AnyLegalWildBall","flawlessIVCount":0,"nature":"Random"},{"id":"wild-338-85","game":"SV","version":"Scarlet/Violet","source":"PKHeX.Core encounter_wild_paldea.pkl","method":"Wild","areaIndex":338,"slotIndex":85,"species":274,"speciesName":"Nuzleaf","speciesNameEn":"Nuzleaf","form":0,"levelMin":14,"levelMax":16,"location":140,"locationName":"Senda Jarana","locationNameEn":"Reveler’s Road","gender":"Random","genderCode":255,"timeFlags":0,"weather":31,"shiny":"Random","shinyLocked":false,"isAlpha":false,"fixedBall":null,"allowedBalls":"AnyLegalWildBall","flawlessIVCount":0,"nature":"Random"},{"id":"wild-266-78","game":"SV","version":"Scarlet/Violet","source":"PKHeX.Core encounter_wild_paldea.pkl","method":"Wild","areaIndex":266,"slotIndex":78,"species":274,"speciesName":"Nuzleaf","speciesNameEn":"Nuzleaf","form":0,"levelMin":58,"levelMax":60,"location":140,"locationName":"Senda Jarana","locationNameEn":"Reveler’s Road","gender":"Random","genderCode":255,"timeFlags":0,"weather":15,"shiny":"Random","shinyLocked":false,"isAlpha":false,"fixedBall":null,"allowedBalls":"AnyLegalWildBall","flawlessIVCount":0,"nature":"Random"},{"id":"wild-266-79","game":"SV","version":"Scarlet/Violet","source":"PKHeX.Core encounter_wild_paldea.pkl","method":"Wild","areaIndex":266,"slotIndex":79,"species":274,"speciesName":"Nuzleaf","speciesNameEn":"Nuzleaf","form":0,"levelMin":58,"levelMax":60,"location":140,"locationName":"Senda Jarana","locationNameEn":"Reveler’s Road","gender":"Random","genderCode":255,"timeFlags":0,"weather":31,"shiny":"Random","shinyLocked":false,"isAlpha":false,"fixedBall":null,"allowedBalls":"AnyLegalWildBall","flawlessIVCount":0,"nature":"Random"},{"id":"wild-331-86","game":"SV","version":"Scarlet/Violet","source":"PKHeX.Core encounter_wild_paldea.pkl","method":"Wild","areaIndex":331,"slotIndex":86,"species":274,"speciesName":"Nuzleaf","speciesNameEn":"Nuzleaf","form":0,"levelMin":58,"levelMax":60,"location":140,"locationName":"Senda Jarana","locationNameEn":"Reveler’s Road","gender":"Random","genderCode":255,"timeFlags":0,"weather":15,"shiny":"Random","shinyLocked":false,"isAlpha":false,"fixedBall":null,"allowedBalls":"AnyLegalWildBall","flawlessIVCount":0,"nature":"Random"},{"id":"wild-331-87","game":"SV","version":"Scarlet/Violet","source":"PKHeX.Core encounter_wild_paldea.pkl","method":"Wild","areaIndex":331,"slotIndex":87,"species":274,"speciesName":"Nuzleaf","speciesNameEn":"Nuzleaf","form":0,"levelMin":58,"levelMax":60,"location":140,"locationName":"Senda Jarana","locationNameEn":"Reveler’s Road","gender":"Random","genderCode":255,"timeFlags":0,"weather":31,"shiny":"Random","shinyLocked":false,"isAlpha":false,"fixedBall":null,"allowedBalls":"AnyLegalWildBall","flawlessIVCount":0,"nature":"Random"},{"id":"wild-338-86","game":"SV","version":"Scarlet/Violet","source":"PKHeX.Core encounter_wild_paldea.pkl","method":"Wild","areaIndex":338,"slotIndex":86,"species":274,"speciesName":"Nuzleaf","speciesNameEn":"Nuzleaf","form":0,"levelMin":58,"levelMax":60,"location":140,"locationName":"Senda Jarana","locationNameEn":"Reveler’s Road","gender":"Random","genderCode":255,"timeFlags":0,"weather":15,"shiny":"Random","shinyLocked":false,"isAlpha":false,"fixedBall":null,"allowedBalls":"AnyLegalWildBall","flawlessIVCount":0,"nature":"Random"},{"id":"wild-338-87","game":"SV","version":"Scarlet/Violet","source":"PKHeX.Core encounter_wild_paldea.pkl","method":"Wild","areaIndex":338,"slotIndex":87,"species":274,"speciesName":"Nuzleaf","speciesNameEn":"Nuzleaf","form":0,"levelMin":58,"levelMax":60,"location":140,"locationName":"Senda Jarana","locationNameEn":"Reveler’s Road","gender":"Random","genderCode":255,"timeFlags":0,"weather":31,"shiny":"Random","shinyLocked":false,"isAlpha":false,"fixedBall":null,"allowedBalls":"AnyLegalWildBall","flawlessIVCount":0,"nature":"Random"},{"id":"wild-304-26","game":"SV","version":"Scarlet/Violet","source":"PKHeX.Core encounter_wild_paldea.pkl","method":"Wild","areaIndex":304,"slotIndex":26,"species":274,"speciesName":"Nuzleaf","speciesNameEn":"Nuzleaf","form":0,"levelMin":50,"levelMax":53,"location":166,"locationName":"Soto Sempiterno","locationNameEn":"Timeless Woods","gender":"Random","genderCode":255,"timeFlags":0,"weather":15,"shiny":"Random","shinyLocked":false,"isAlpha":false,"fixedBall":null,"allowedBalls":"AnyLegalWildBall","flawlessIVCount":0,"nature":"Random"},{"id":"wild-311-100","game":"SV","version":"Scarlet/Violet","source":"PKHeX.Core encounter_wild_paldea.pkl","method":"Wild","areaIndex":311,"slotIndex":100,"species":274,"speciesName":"Nuzleaf","speciesNameEn":"Nuzleaf","form":0,"levelMin":50,"levelMax":53,"location":166,"locationName":"Soto Sempiterno","locationNameEn":"Timeless Woods","gender":"Random","genderCode":255,"timeFlags":0,"weather":15,"shiny":"Random","shinyLocked":false,"isAlpha":false,"fixedBall":null,"allowedBalls":"AnyLegalWildBall","flawlessIVCount":0,"nature":"Random"},{"id":"wild-311-101","game":"SV","version":"Scarlet/Violet","source":"PKHeX.Core encounter_wild_paldea.pkl","method":"Wild","areaIndex":311,"slotIndex":101,"species":274,"speciesName":"Nuzleaf","speciesNameEn":"Nuzleaf","form":0,"levelMin":50,"levelMax":53,"location":166,"locationName":"Soto Sempiterno","locationNameEn":"Timeless Woods","gender":"Random","genderCode":255,"timeFlags":0,"weather":31,"shiny":"Random","shinyLocked":false,"isAlpha":false,"fixedBall":null,"allowedBalls":"AnyLegalWildBall","flawlessIVCount":0,"nature":"Random"},{"id":"wild-312-100","game":"SV","version":"Scarlet/Violet","source":"PKHeX.Core encounter_wild_paldea.pkl","method":"Wild","areaIndex":312,"slotIndex":100,"species":274,"speciesName":"Nuzleaf","speciesNameEn":"Nuzleaf","form":0,"levelMin":50,"levelMax":53,"location":166,"locationName":"Soto Sempiterno","locationNameEn":"Timeless Woods","gender":"Random","genderCode":255,"timeFlags":0,"weather":15,"shiny":"Random","shinyLocked":false,"isAlpha":false,"fixedBall":null,"allowedBalls":"AnyLegalWildBall","flawlessIVCount":0,"nature":"Random"},{"id":"wild-312-101","game":"SV","version":"Scarlet/Violet","source":"PKHeX.Core encounter_wild_paldea.pkl","method":"Wild","areaIndex":312,"slotIndex":101,"species":274,"speciesName":"Nuzleaf","speciesNameEn":"Nuzleaf","form":0,"levelMin":50,"levelMax":53,"location":166,"locationName":"Soto Sempiterno","locationNameEn":"Timeless Woods","gender":"Random","genderCode":255,"timeFlags":0,"weather":31,"shiny":"Random","shinyLocked":false,"isAlpha":false,"fixedBall":null,"allowedBalls":"AnyLegalWildBall","flawlessIVCount":0,"nature":"Random"},{"id":"wild-313-100","game":"SV","version":"Scarlet/Violet","source":"PKHeX.Core encounter_wild_paldea.pkl","method":"Wild","areaIndex":313,"slotIndex":100,"species":274,"speciesName":"Nuzleaf","speciesNameEn":"Nuzleaf","form":0,"levelMin":50,"levelMax":53,"location":166,"locationName":"Soto Sempiterno","locationNameEn":"Timeless Woods","gender":"Random","genderCode":255,"timeFlags":0,"weather":15,"shiny":"Random","shinyLocked":false,"isAlpha":false,"fixedBall":null,"allowedBalls":"AnyLegalWildBall","flawlessIVCount":0,"nature":"Random"},{"id":"wild-313-101","game":"SV","version":"Scarlet/Violet","source":"PKHeX.Core encounter_wild_paldea.pkl","method":"Wild","areaIndex":313,"slotIndex":101,"species":274,"speciesName":"Nuzleaf","speciesNameEn":"Nuzleaf","form":0,"levelMin":50,"levelMax":53,"location":166,"locationName":"Soto Sempiterno","locationNameEn":"Timeless Woods","gender":"Random","genderCode":255,"timeFlags":0,"weather":31,"shiny":"Random","shinyLocked":false,"isAlpha":false,"fixedBall":null,"allowedBalls":"AnyLegalWildBall","flawlessIVCount":0,"nature":"Random"},{"id":"wild-304-27","game":"SV","version":"Scarlet/Violet","source":"PKHeX.Core encounter_wild_paldea.pkl","method":"Wild","areaIndex":304,"slotIndex":27,"species":274,"speciesName":"Nuzleaf","speciesNameEn":"Nuzleaf","form":0,"levelMin":71,"levelMax":74,"location":166,"locationName":"Soto Sempiterno","locationNameEn":"Timeless Woods","gender":"Random","genderCode":255,"timeFlags":0,"weather":15,"shiny":"Random","shinyLocked":false,"isAlpha":false,"fixedBall":null,"allowedBalls":"AnyLegalWildBall","flawlessIVCount":0,"nature":"Random"},{"id":"wild-311-102","game":"SV","version":"Scarlet/Violet","source":"PKHeX.Core encounter_wild_paldea.pkl","method":"Wild","areaIndex":311,"slotIndex":102,"species":274,"speciesName":"Nuzleaf","speciesNameEn":"Nuzleaf","form":0,"levelMin":71,"levelMax":74,"location":166,"locationName":"Soto Sempiterno","locationNameEn":"Timeless Woods","gender":"Random","genderCode":255,"timeFlags":0,"weather":15,"shiny":"Random","shinyLocked":false,"isAlpha":false,"fixedBall":null,"allowedBalls":"AnyLegalWildBall","flawlessIVCount":0,"nature":"Random"},{"id":"wild-311-103","game":"SV","version":"Scarlet/Violet","source":"PKHeX.Core encounter_wild_paldea.pkl","method":"Wild","areaIndex":311,"slotIndex":103,"species":274,"speciesName":"Nuzleaf","speciesNameEn":"Nuzleaf","form":0,"levelMin":71,"levelMax":74,"location":166,"locationName":"Soto Sempiterno","locationNameEn":"Timeless Woods","gender":"Random","genderCode":255,"timeFlags":0,"weather":31,"shiny":"Random","shinyLocked":false,"isAlpha":false,"fixedBall":null,"allowedBalls":"AnyLegalWildBall","flawlessIVCount":0,"nature":"Random"},{"id":"wild-312-102","game":"SV","version":"Scarlet/Violet","source":"PKHeX.Core encounter_wild_paldea.pkl","method":"Wild","areaIndex":312,"slotIndex":102,"species":274,"speciesName":"Nuzleaf","speciesNameEn":"Nuzleaf","form":0,"levelMin":71,"levelMax":74,"location":166,"locationName":"Soto Sempiterno","locationNameEn":"Timeless Woods","gender":"Random","genderCode":255,"timeFlags":0,"weather":15,"shiny":"Random","shinyLocked":false,"isAlpha":false,"fixedBall":null,"allowedBalls":"AnyLegalWildBall","flawlessIVCount":0,"nature":"Random"},{"id":"wild-312-103","game":"SV","version":"Scarlet/Violet","source":"PKHeX.Core encounter_wild_paldea.pkl","method":"Wild","areaIndex":312,"slotIndex":103,"species":274,"speciesName":"Nuzleaf","speciesNameEn":"Nuzleaf","form":0,"levelMin":71,"levelMax":74,"location":166,"locationName":"Soto Sempiterno","locationNameEn":"Timeless Woods","gender":"Random","genderCode":255,"timeFlags":0,"weather":31,"shiny":"Random","shinyLocked":false,"isAlpha":false,"fixedBall":null,"allowedBalls":"AnyLegalWildBall","flawlessIVCount":0,"nature":"Random"},{"id":"wild-313-102","game":"SV","version":"Scarlet/Violet","source":"PKHeX.Core encounter_wild_paldea.pkl","method":"Wild","areaIndex":313,"slotIndex":102,"species":274,"speciesName":"Nuzleaf","speciesNameEn":"Nuzleaf","form":0,"levelMin":71,"levelMax":74,"location":166,"locationName":"Soto Sempiterno","locationNameEn":"Timeless Woods","gender":"Random","genderCode":255,"timeFlags":0,"weather":15,"shiny":"Random","shinyLocked":false,"isAlpha":false,"fixedBall":null,"allowedBalls":"AnyLegalWildBall","flawlessIVCount":0,"nature":"Random"},{"id":"wild-313-103","game":"SV","version":"Scarlet/Violet","source":"PKHeX.Core encounter_wild_paldea.pkl","method":"Wild","areaIndex":313,"slotIndex":103,"species":274,"speciesName":"Nuzleaf","speciesNameEn":"Nuzleaf","form":0,"levelMin":71,"levelMax":74,"location":166,"locationName":"Soto Sempiterno","locationNameEn":"Timeless Woods","gender":"Random","genderCode":255,"timeFlags":0,"weather":31,"shiny":"Random","shinyLocked":false,"isAlpha":false,"fixedBall":null,"allowedBalls":"AnyLegalWildBall","flawlessIVCount":0,"nature":"Random"}]