[{"id":"fixed-100","game":"SV","version":"Scarlet/Violet","source":"PKHeX.Core encounter_fixed_paldea.pkl","method":"Fixed Spawn","species":80,"speciesName":"Slowbro","speciesNameEn":"Slowbro","form":0,"levelMin":45,"levelMax":45,"location":40,"locationName":"Lago Cazola","locationNameEn":"Casseroya Lake","extraLocations":[40],"gender":"Random","genderCode":255,"ability":"Any12","shiny":"Random","shinyLocked":false,"fixedBall":null,"allowedBalls":"AnyLegalWildBall","flawlessIVCount":0,"teraType":"Normal","moves":[0,0,0,0],"nature":"Random"},{"id":"fixed-101","game":"SV","version":"Scarlet/Violet","source":"PKHeX.Core encounter_fixed_paldea.pkl","method":"Fixed Spawn","species":80,"speciesName":"Slowbro","speciesNameEn":"Slowbro","form":0,"levelMin":55,"levelMax":55,"location":40,"locationName":"Lago Cazola","locationNameEn":"Casseroya Lake","extraLocations":[40],"gender":"Random","genderCode":255,"ability":"Any12","shiny":"Random","shinyLocked":false,"fixedBall":null,"allowedBalls":"AnyLegalWildBall","flawlessIVCount":3,"teraType":"Psychic","moves":[447,94,57,303],"nature":"Random"},{"id":"tera-paldea-19","game":"SV","version":"Scarlet/Violet","source":"PKHeX.Core encounter_gem_paldea.pkl","method":"Tera Raid","map":"Paldea","species":80,"speciesName":"Slowbro","speciesNameEn":"Slowbro","form":0,"levelMin":75,"levelMax":75,"location":30024,"locationName":"Cueva cristalina","locationNameEn":"a crystal cavern","gender":"SpeciesRatio","genderCode":-1,"ability":"Any12H","shiny":"Random","shinyLocked":false,"fixedBall":null,"allowedBalls":"AnyLegalWildBall","flawlessIVCount":4,"teraType":"Fighting","moves":[428,710,281,352],"raidStars":5,"raidIndex":0,"randRate":100,"availableScarlet":true,"availableViolet":true,"nature":"Random"},{"id":"wild-11-3","game":"SV","version":"Scarlet/Violet","source":"PKHeX.Core encounter_wild_paldea.pkl","method":"Wild","areaIndex":11,"slotIndex":3,"species":80,"speciesName":"Slowbro","speciesNameEn":"Slowbro","form":0,"levelMin":52,"levelMax":56,"location":109,"locationName":"Alameda Socarrada","locationNameEn":"Socarrat Trail","gender":"Random","genderCode":255,"timeFlags":0,"weather":15,"shiny":"Random","shinyLocked":false,"isAlpha":false,"fixedBall":null,"allowedBalls":"AnyLegalWildBall","flawlessIVCount":0,"nature":"Random"},{"id":"wild-39-3","game":"SV","version":"Scarlet/Violet","source":"PKHeX.Core encounter_wild_paldea.pkl","method":"Wild","areaIndex":39,"slotIndex":3,"species":80,"speciesName":"Slowbro","speciesNameEn":"Slowbro","form":0,"levelMin":52,"levelMax":56,"location":109,"locationName":"Alameda Socarrada","locationNameEn":"Socarrat Trail","gender":"Random","genderCode":255,"timeFlags":0,"weather":15,"shiny":"Random","shinyLocked":false,"isAlpha":false,"fixedBall":null,"allowedBalls":"AnyLegalWildBall","flawlessIVCount":0,"nature":"Random"},{"id":"wild-225-4","game":"SV","version":"Scarlet/Violet","source":"PKHeX.Core encounter_wild_paldea.pkl","method":"Wild","areaIndex":225,"slotIndex":4,"species":80,"speciesName":"Slowbro","speciesNameEn":"Slowbro","form":0,"levelMin":49,"levelMax":55,"location":40,"locationName":"Lago Cazola","locationNameEn":"Casseroya Lake","gender":"Random","genderCode":255,"timeFlags":0,"weather":15,"shiny":"Random","shinyLocked":false,"isAlpha":false,"fixedBall":null,"allowedBalls":"AnyLegalWildBall","flawlessIVCount":0,"nature":"Random"},{"id":"wild-27-2","game":"SV","version":"Scarlet/Violet","source":"PKHeX.Core encounter_wild_paldea.pkl","method":"Wild","areaIndex":27,"slotIndex":2,"species":80,"speciesName":"Slowbro","speciesNameEn":"Slowbro","form":0,"levelMin":49,"levelMax":56,"location":40,"locationName":"Lago Cazola","locationNameEn":"Casseroya Lake","gender":"Random","genderCode":255,"timeFlags":0,"weather":15,"shiny":"Random","shinyLocked":false,"isAlpha":false,"fixedBall":null,"allowedBalls":"AnyLegalWildBall","flawlessIVCount":0,"nature":"Random"},{"id":"wild-6-6","game":"SV","version":"Scarlet/Violet","source":"PKHeX.Core encounter_wild_paldea.pkl","method":"Wild","areaIndex":6,"slotIndex":6,"species":80,"speciesName":"Slowbro","speciesNameEn":"Slowbro","form":0,"levelMin":49,"levelMax":56,"location":40,"locationName":"Lago Cazola","locationNameEn":"Casseroya Lake","gender":"Random","genderCode":255,"timeFlags":0,"weather":15,"shiny":"Random","shinyLocked":false,"isAlpha":false,"fixedBall":null,"allowedBalls":"AnyLegalWildBall","flawlessIVCount":0,"nature":"Random"},{"id":"wild-174-2","game":"SV","version":"Scarlet/Violet","source":"PKHeX.Core encounter_wild_paldea.pkl","method":"Wild","areaIndex":174,"slotIndex":2,"species":80,"speciesName":"Slowbro","speciesNameEn":"Slowbro","form":0,"levelMin":50,"levelMax":54,"location":40,"locationName":"Lago Cazola","locationNameEn":"Casseroya Lake","gender":"Random","genderCode":255,"timeFlags":0,"weather":15,"shiny":"Random","shinyLocked":false,"isAlpha":false,"fixedBall":null,"allowedBalls":"AnyLegalWildBall","flawlessIVCount":0,"nature":"Random"},{"id":"wild-124-3","game":"SV","version":"Scarlet/Violet","source":"PKHeX.Core encounter_wild_paldea.pkl","method":"Wild","areaIndex":124,"slotIndex":3,"species":80,"speciesName":"Slowbro","speciesNameEn":"Slowbro","form":0,"levelMin":51,"levelMax":56,"location":40,"locationName":"Lago Cazola","locationNameEn":"Casseroya Lake","gender":"Random","genderCode":255,"timeFlags":0,"weather":111,"shiny":"Random","shinyLocked":false,"isAlpha":false,"fixedBall":null,"allowedBalls":"AnyLegalWildBall","flawlessIVCount":0,"nature":"Random"},{"id":"wild-225-5","game":"SV","version":"Scarlet/Violet","source":"PKHeX.Core encounter_wild_paldea.pkl","method":"Wild","areaIndex":225,"slotIndex":5,"species":80,"speciesName":"Slowbro","speciesNameEn":"Slowbro","form":0,"levelMin":51,"levelMax":55,"location":40,"locationName":"Lago Cazola","locationNameEn":"Casseroya Lake","gender":"Random","genderCode":255,"timeFlags":0,"weather":111,"shiny":"Random","shinyLocked":false,"isAlpha":false,"fixedBall":null,"allowedBalls":"AnyLegalWildBall","flawlessIVCount":0,"nature":"Random"},{"id":"wild-6-7","game":"SV","version":"Scarlet/Violet","source":"PKHeX.Core encounter_wild_paldea.pkl","method":"Wild","areaIndex":6,"slotIndex":7,"species":80,"speciesName":"Slowbro","speciesNameEn":"Slowbro","form":0,"levelMin":51,"levelMax":56,"location":40,"locationName":"Lago Cazola","locationNameEn":"Casseroya Lake","gender":"Random","genderCode":255,"timeFlags":0,"weather":111,"shiny":"Random","shinyLocked":false,"isAlpha":false,"fixedBall":null,"allowedBalls":"AnyLegalWildBall","flawlessIVCount":0,"nature":"Random"},{"id":"wild-40-3","game":"SV","version":"Scarlet/Violet","source":"PKHeX.Core encounter_wild_paldea.pkl","method":"Wild","areaIndex":40,"slotIndex":3,"species":80,"speciesName":"Slowbro","speciesNameEn":"Slowbro","form":0,"levelMin":52,"levelMax":56,"location":40,"locationName":"Lago Cazola","locationNameEn":"Casseroya Lake","gender":"Random","genderCode":255,"timeFlags":0,"weather":15,"shiny":"Random","shinyLocked":false,"isAlpha":false,"fixedBall":null,"allowedBalls":"AnyLegalWildBall","flawlessIVCount":0,"nature":"Random"},{"id":"wild-223-12","game":"SV","version":"Scarlet/Violet","source":"PKHeX.Core encounter_wild_paldea.pkl","method":"Wild","areaIndex":223,"slotIndex":12,"species":80,"speciesName":"Slowbro","speciesNameEn":"Slowbro","form":0,"levelMin":49,"levelMax":54,"location":26,"locationName":"Área 2 (Oeste)","locationNameEn":"West Province (Area Two)","gender":"Random","genderCode":255,"timeFlags":0,"weather":15,"shiny":"Random","shinyLocked":false,"isAlpha":false,"fixedBall":null,"allowedBalls":"AnyLegalWildBall","flawlessIVCount":0,"nature":"Random"},{"id":"wild-24-16","game":"SV","version":"Scarlet/Violet","source":"PKHeX.Core encounter_wild_paldea.pkl","method":"Wild","areaIndex":24,"slotIndex":16,"species":80,"speciesName":"Slowbro","speciesNameEn":"Slowbro","form":0,"levelMin":49,"levelMax":54,"location":26,"locationName":"Área 2 (Oeste)","locationNameEn":"West Province (Area Two)","gender":"Random","genderCode":255,"timeFlags":0,"weather":15,"shiny":"Random","shinyLocked":false,"isAlpha":false,"fixedBall":null,"allowedBalls":"AnyLegalWildBall","flawlessIVCount":0,"nature":"Random"},{"id":"wild-7-10","game":"SV","version":"Scarlet/Violet","source":"PKHeX.Core encounter_wild_paldea.pkl","method":"Wild","areaIndex":7,"slotIndex":10,"species":80,"speciesName":"Slowbro","speciesNameEn":"Slowbro","form":0,"levelMin":49,"levelMax":54,"location":26,"locationName":"Área 2 (Oeste)","locationNameEn":"West Province (Area Two)","gender":"Random","genderCode":255,"timeFlags":0,"weather":15,"shiny":"Random","shinyLocked":false,"isAlpha":false,"fixedBall":null,"allowedBalls":"AnyLegalWildBall","flawlessIVCount":0,"nature":"Random"}]