[{"id":"hyperspace-0-563","game":"ZA","source":"PKHeX.Core encounter_hyperspace_za.pkl","method":"Hyperspace","slotType":"Hyperspace","areaIndex":0,"slotIndex":563,"species":433,"speciesName":"Chingling","speciesNameEn":"Chingling","form":0,"levelMin":14,"levelMax":16,"location":273,"locationName":"Luminalia Dimensional","locationNameEn":"Hyperspace Lumiose","gender":"Random","genderCode":255,"shiny":"Random","shinyLocked":false,"isAlpha":false,"fixedBall":null,"allowedBalls":"AnyLegalWildBall","flawlessIVCount":0,"nature":"Random"},{"id":"hyperspace-0-561","game":"ZA","source":"PKHeX.Core encounter_hyperspace_za.pkl","method":"Hyperspace","slotType":"Hyperspace","areaIndex":0,"slotIndex":561,"species":433,"speciesName":"Chingling","speciesNameEn":"Chingling","form":0,"levelMin":21,"levelMax":23,"location":273,"locationName":"Luminalia Dimensional","locationNameEn":"Hyperspace Lumiose","gender":"Random","genderCode":255,"shiny":"Random","shinyLocked":false,"isAlpha":false,"fixedBall":null,"allowedBalls":"AnyLegalWildBall","flawlessIVCount":0,"nature":"Random"},{"id":"hyperspace-0-562","game":"ZA","source":"PKHeX.Core encounter_hyperspace_za.pkl","method":"Hyperspace","slotType":"Hyperspace","areaIndex":0,"slotIndex":562,"species":433,"speciesName":"Chingling","speciesNameEn":"Chingling","form":0,"levelMin":23,"levelMax":25,"location":273,"locationName":"Luminalia Dimensional","locationNameEn":"Hyperspace Lumiose","gender":"Random","genderCode":255,"shiny":"Random","shinyLocked":false,"isAlpha":true,"fixedBall":null,"allowedBalls":"AnyLegalWildBall","flawlessIVCount":3,"nature":"Random"},{"id":"hyperspace-0-560","game":"ZA","source":"PKHeX.Core encounter_hyperspace_za.pkl","method":"Hyperspace","slotType":"Hyperspace","areaIndex":0,"slotIndex":560,"species":433,"speciesName":"Chingling","speciesNameEn":"Chingling","form":0,"levelMin":30,"levelMax":32,"location":273,"locationName":"Luminalia Dimensional","locationNameEn":"Hyperspace Lumiose","gender":"Random","genderCode":255,"shiny":"Random","shinyLocked":false,"isAlpha":true,"fixedBall":null,"allowedBalls":"AnyLegalWildBall","flawlessIVCount":3,"nature":"Random"}]